cookie_thief/__init__.py
cookie_thief/base.py
cookie_thief-0.0.1.dist-info/LICENSE
cookie_thief-0.0.1.dist-info/METADATA
cookie_thief-0.0.1.dist-info/WHEEL
cookie_thief-0.0.1.dist-info/top_level.txt
cookie_thief-0.0.1.dist-info/RECORD
