Metadata-Version: 2.1
Name: cookie-thief
Version: 0.0.1
Summary: A class that steals cookies from a website
Home-page: https://github.com/ProfHercules/cookie_thief
Author: Hercules Smith
Author-email: hercosmith03@gmail.com
License: UNKNOWN
Project-URL: Bug Tracker, https://github.com/ProfHercules/cookie_thief/issues
Platform: UNKNOWN
Classifier: Programming Language :: Python :: 3
Classifier: Operating System :: OS Independent
Requires-Python: >=3.9
License-File: LICENSE
